logprov/__init__.py
logprov/capture.py
logprov/io.py
logprov-0.0.2.dist-info/METADATA
logprov-0.0.2.dist-info/WHEEL
logprov-0.0.2.dist-info/top_level.txt
logprov-0.0.2.dist-info/RECORD
