Metadata-Version: 2.1
Name: logprov
Version: 0.0.2
Summary: capture of provenance information into structured logs
Home-page: https://github.com/mservillat/logprov
Author: Mathieu Servillat & Jose Enrique Ruiz
Author-email: mathieu.servillat@obspm.fr, jer@iaa.es
License: UNKNOWN
Platform: UNKNOWN
Classifier: Programming Language :: Python :: 3
Classifier: License :: OSI Approved :: MIT License
Classifier: Operating System :: OS Independent
Requires-Python: >=3.6
